textual_utils/__init__.py
textual_utils/about_header_icon.py
textual_utils/about_screen.tcss
textual_utils/app_metadata.py
textual_utils/confirm_screen.tcss
textual_utils/py.typed
textual_utils/screens.py
textual_utils/screens.tcss
textual_utils/settings_screen.tcss
textual_utils-2.1.0.dist-info/METADATA
textual_utils-2.1.0.dist-info/WHEEL
textual_utils-2.1.0.dist-info/licenses/LICENSE
textual_utils-2.1.0.dist-info/RECORD
