Metadata-Version: 2.4
Name: textual-utils
Version: 2.1.0
Summary: Utilities for use with the Textual package
Author-email: Rafal Padkowski <rafaelp@poczta.onet.pl>
License-Expression: MIT
License-File: LICENSE
Requires-Python: >=3.13
Requires-Dist: config
Requires-Dist: i18n
Requires-Dist: textual>=6.3.0
